setup.py
distofgaussbinmadebyashu/Binomialdistribution.py
distofgaussbinmadebyashu/Gaussiandistribution.py
distofgaussbinmadebyashu/Generaldistribution.py
distofgaussbinmadebyashu/__init__.py
distofgaussbinmadebyashu.egg-info/PKG-INFO
distofgaussbinmadebyashu.egg-info/SOURCES.txt
distofgaussbinmadebyashu.egg-info/dependency_links.txt
distofgaussbinmadebyashu.egg-info/not-zip-safe
distofgaussbinmadebyashu.egg-info/top_level.txt